pymlpipe/.git/FETCH_HEAD
pymlpipe/.git/HEAD
pymlpipe/.git/ORIG_HEAD
pymlpipe/.git/config
pymlpipe/.git/description
pymlpipe/.git/hooks/applypatch-msg.sample
pymlpipe/.git/hooks/commit-msg.sample
pymlpipe/.git/hooks/fsmonitor-watchman.sample
pymlpipe/.git/hooks/post-update.sample
pymlpipe/.git/hooks/pre-applypatch.sample
pymlpipe/.git/hooks/pre-commit.sample
pymlpipe/.git/hooks/pre-merge-commit.sample
pymlpipe/.git/hooks/pre-push.sample
pymlpipe/.git/hooks/pre-rebase.sample
pymlpipe/.git/hooks/pre-receive.sample
pymlpipe/.git/hooks/prepare-commit-msg.sample
pymlpipe/.git/hooks/push-to-checkout.sample
pymlpipe/.git/hooks/update.sample
pymlpipe/.git/index
pymlpipe/.git/info/exclude
pymlpipe/.git/logs/HEAD
pymlpipe/.git/logs/refs/heads/main
pymlpipe/.git/logs/refs/remotes/origin/HEAD
pymlpipe/.git/logs/refs/remotes/origin/dev
pymlpipe/.git/logs/refs/remotes/origin/main
pymlpipe/.git/objects/00/d990c8a7526fae5a737666e4881a6b20896d46
pymlpipe/.git/objects/09/8b774b782e06caa328e1de67d688aa34d5f8a7
pymlpipe/.git/objects/0c/7d1562fadac348458649704caaf0e26e637839
pymlpipe/.git/objects/0e/523e1d8c8f7165ae6fd573a08d9c90b7ccdcc8
pymlpipe/.git/objects/10/3f5bff1e6aa2413d60a2f72e833453e2601d8b
pymlpipe/.git/objects/13/919b9ea7abc0d8f8c8f3a5e5a889dd86174b88
pymlpipe/.git/objects/21/a4aa944f744302fef4ab642cf6e10c757449f8
pymlpipe/.git/objects/23/df31fb7777b2881928cec73892f3108c850603
pymlpipe/.git/objects/32/4f92f39c0c1187db0acf5aec742f7a1880d58c
pymlpipe/.git/objects/33/d04a70708fbbc2af52db302a69829af371a779
pymlpipe/.git/objects/35/c513dd925e6848a93eb569f8268b0f2711529d
pymlpipe/.git/objects/37/935bf58fd64ecf301de381715e246dd851cd88
pymlpipe/.git/objects/39/c88654b9a09d7a1f34dfa59c2bb2dcbef044a9
pymlpipe/.git/objects/3b/03ef7bd069b2ac27d44d45e0635cd2684b56db
pymlpipe/.git/objects/41/d26d90cde7620cf1355122bd5200ec763286db
pymlpipe/.git/objects/44/d4b21d4902aef2cc8122871fd377ade6bd2a32
pymlpipe/.git/objects/51/1e3bcad7515ac158209ee27d232a1183435d29
pymlpipe-0.2.9.dist-info/entry_points.txt
pymlpipe-0.2.9.dist-info/WHEEL
pymlpipe-0.2.9.dist-info/METADATA
pymlpipe-0.2.9.dist-info/RECORD
