Metadata-Version: 2.1
Name: pymlpipe
Version: 0.2.9
Summary: PyMLpipe is a Python library for ease Machine Learning Model monitering and Deployment.
Home-page: https://github.com/neelindresh/pymlpipe
License: MIT
Keywords: MlOps,Machine Learning,Monitering,Deployment,XAI,Pipeline
Author: Indresh Bhattacharya
Author-email: indresh2neel@gmail.com
Requires-Python: >=3.6,<3.10
Classifier: Development Status :: 4 - Beta
Classifier: Framework :: Flask
Classifier: License :: Freely Distributable
Classifier: License :: OSI Approved :: MIT License
Classifier: Operating System :: MacOS :: MacOS X
Classifier: Programming Language :: ML
Classifier: Programming Language :: Python :: 3
Classifier: Programming Language :: Python :: 3.6
Classifier: Programming Language :: Python :: 3.7
Classifier: Programming Language :: Python :: 3.8
Classifier: Programming Language :: Python :: 3.9
Classifier: Programming Language :: Python :: Implementation
Requires-Dist: Flask (>=2.1.2,<3.0.0)
Requires-Dist: Flask-API (>=3.0.post1,<4.0)
Requires-Dist: PyYAML (>=6.0,<7.0)
Requires-Dist: catboost (>=1.1.1,<2.0.0)
Requires-Dist: cloudpickle (>=2.2.1,<3.0.0)
Requires-Dist: lightgbm (>=3.3.5,<4.0.0)
Requires-Dist: matplotlib (==3.6.3)
Requires-Dist: pandas (>=1.4.3,<2.0.0)
Requires-Dist: shap (>=0.41.0,<0.42.0)
Requires-Dist: sklearn (>=0.0,<0.1)
Requires-Dist: torch (>=1.12.0,<2.0.0)
Requires-Dist: tqdm (>=4.64.1,<5.0.0)
Requires-Dist: xgboost (>=1.7.3,<2.0.0)
Project-URL: Documentation, https://neelindresh.github.io/pymlpipe.documentation.io/
Project-URL: Repository, https://github.com/neelindresh/pymlpipe
